__init__.py
wikipedia_summary.py
model/__init__.py
model/wikipediapage.py
wikiutil/__init__.py
wikiutil/fetcher.py
wikipediasummary-1.1.4.dist-info/METADATA
wikipediasummary-1.1.4.dist-info/WHEEL
wikipediasummary-1.1.4.dist-info/licenses/LICENSE
wikipediasummary-1.1.4.dist-info/RECORD
