Metadata-Version: 2.1
Name: wikipediasummary
Version: 1.1.4
Summary: Utility package for fetching summaries of Wikipedia pages
Project-URL: Homepage, https://github.com/jamilkarami/wikipediasummary
Project-URL: Bug Tracker, https://github.com/jamilkarami/wikipediasummary/issues
Author: Jamil Karami
License-File: LICENSE
Classifier: Operating System :: OS Independent
Classifier: Programming Language :: Python :: 3
Requires-Python: >=3.7
